watsor/__init__.py
watsor/engine.py
watsor/main.py
watsor/main_for_gpu.py
watsor/zones.py
watsor/config/__init__.py
watsor/config/coco.py
watsor/config/loader.py
watsor/config/schema.py
watsor/detection/__init__.py
watsor/detection/detector.py
watsor/detection/devices.py
watsor/detection/edge_tpu.py
watsor/detection/tensorflow_cpu.py
watsor/detection/tensorflow_lite_cpu.py
watsor/detection/tensorrt_gpu.py
watsor/filter/__init__.py
watsor/filter/area.py
watsor/filter/confidence.py
watsor/filter/mask.py
watsor/filter/sieve.py
watsor/filter/track.py
watsor/output/__init__.py
watsor/output/blend.py
watsor/output/copy.py
watsor/output/draw.py
watsor/output/mqtt.py
watsor/output/snapshot.py
watsor/output/video.py
watsor/stream/__init__.py
watsor/stream/copy.py
watsor/stream/ffmpeg.py
watsor/stream/log.py
watsor/stream/publish.py
watsor/stream/read.py
watsor/stream/share.py
watsor/stream/spin.py
watsor/stream/sync.py
watsor/stream/watch.py
watsor/stream/work.py
watsor/test/__init__.py
watsor/test/detect_stream.py
watsor/test/dummy_stream.py
watsor/test/numpy_stream.py
watsor/test/test_config.py
watsor/test/test_detect.py
watsor/test/test_ffmpeg.py
watsor/test/test_filter.py
watsor/test/test_output.py
watsor/test/test_share.py
watsor/test/test_spawn.py
watsor/test/test_stream.py
watsor/test/test_sync.py
watsor/test/test_watch.py
watsor-1.0.8.dist-info/LICENSE
watsor-1.0.8.dist-info/METADATA
watsor-1.0.8.dist-info/WHEEL
watsor-1.0.8.dist-info/top_level.txt
watsor-1.0.8.dist-info/RECORD
