Metadata-Version: 2.1
Name: watsor
Version: 1.0.8
Summary: Object detection for video surveillance
Home-page: https://github.com/asmirnou/watsor
Author: Alexander Smirnov
Author-email: aliaksandr.smirnou@gmail.com
License: MIT License
Keywords: object person detection video IP camera realtime stream ffmpeg RTSP surveillance
Classifier: Programming Language :: Python :: 3
Classifier: License :: OSI Approved :: MIT License
Classifier: Operating System :: OS Independent
Requires-Python: >=3.6
License-File: LICENSE
Requires-Dist: PyYaml
Requires-Dist: Pillow
Requires-Dist: cerberus
Requires-Dist: numpy
Requires-Dist: scipy
Requires-Dist: opencv-python-headless
Requires-Dist: shapely
Requires-Dist: werkzeug
Requires-Dist: paho-mqtt
Provides-Extra: coral
Requires-Dist: edgetpu ; extra == 'coral'
Provides-Extra: cpu
Requires-Dist: tensorflow ; extra == 'cpu'
Provides-Extra: cuda
Requires-Dist: pycuda ; extra == 'cuda'
Requires-Dist: tensorrt ; extra == 'cuda'
Provides-Extra: dev
Requires-Dist: coverage ; extra == 'dev'
Provides-Extra: lite
Requires-Dist: tflite-runtime ; extra == 'lite'
